files_to_dataframe/__init__.py
files_to_dataframe/files_to_dataframe_fn.py
files_to_dataframe-0.0.1.dist-info/LICENSE.txt
files_to_dataframe-0.0.1.dist-info/METADATA
files_to_dataframe-0.0.1.dist-info/WHEEL
files_to_dataframe-0.0.1.dist-info/top_level.txt
files_to_dataframe-0.0.1.dist-info/RECORD
